otel_custom_distro/__init__.py
otel_custom_distro/distro.py
otel_custom_distro/instrumentation_registry.py
odigos_python_distro-0.1.0.dist-info/METADATA
odigos_python_distro-0.1.0.dist-info/WHEEL
odigos_python_distro-0.1.0.dist-info/entry_points.txt
odigos_python_distro-0.1.0.dist-info/top_level.txt
odigos_python_distro-0.1.0.dist-info/RECORD
