Metadata-Version: 2.1
Name: odigos-python-distro
Version: 0.1.0
Summary: Odigos Python Distro
